MANIFEST.in
README.md
setup.py
ffmpegbin/GPLv3.txt
ffmpegbin/ffmpeg
ffmpegbin/ffmpegbin.py
ffmpegbin/ffprobe
ffmpegbin/qt-faststart
ffmpegbin/readme.txt
ffmpegbin.egg-info/PKG-INFO
ffmpegbin.egg-info/SOURCES.txt
ffmpegbin.egg-info/dependency_links.txt
ffmpegbin.egg-info/top_level.txt